nlp_suite/__init__.py
usool_e_ghalib-0.1.0.dist-info/METADATA
usool_e_ghalib-0.1.0.dist-info/WHEEL
usool_e_ghalib-0.1.0.dist-info/RECORD
