Metadata-Version: 2.4
Name: usool-e-ghalib
Version: 0.1.0
Summary: A comprehensive NLP toolkit combining all major Python NLP libraries
License: MIT
Keywords: nlp,natural-language-processing,machine-learning,ai,text-analysis
Author: Sunil Kumar Pradhan
Author-email: sunilkumarweb47@gmail.com
Requires-Python: >=3.8.1,<4.0.0
Classifier: Development Status :: 3 - Alpha
Classifier: Intended Audience :: Developers
Classifier: Intended Audience :: Science/Research
Classifier: License :: OSI Approved :: MIT License
Classifier: Programming Language :: Python :: 3
Classifier: Programming Language :: Python :: 3.9
Classifier: Programming Language :: Python :: 3.10
Classifier: Programming Language :: Python :: 3.11
Classifier: Programming Language :: Python :: 3.12
Classifier: Programming Language :: Python :: 3.13
Classifier: Programming Language :: Python :: 3.14
Classifier: Programming Language :: Python :: 3.8
Classifier: Topic :: Scientific/Engineering :: Artificial Intelligence
Classifier: Topic :: Text Processing :: Linguistic
Provides-Extra: advanced
Provides-Extra: all
Provides-Extra: basic
Provides-Extra: complete
Provides-Extra: core
Provides-Extra: deep-learning
Provides-Extra: evaluation
Provides-Extra: preprocessing
Provides-Extra: sentiment
Provides-Extra: serving
Provides-Extra: speech
Provides-Extra: topic-modeling
Provides-Extra: translation
Provides-Extra: vectorization
Provides-Extra: visualization
Requires-Dist: SpeechRecognition (>=3.9,<4.0) ; extra == "speech" or extra == "all"
Requires-Dist: beautifulsoup4 (>=4.11,<5.0) ; extra == "preprocessing" or extra == "all"
Requires-Dist: bertopic (>=0.12,<0.13) ; extra == "topic-modeling" or extra == "all"
Requires-Dist: clean-text (>=0.6,<0.7) ; extra == "preprocessing" or extra == "all"
Requires-Dist: deep-translator (>=1.9,<2.0) ; extra == "translation" or extra == "all"
Requires-Dist: evaluate (>=0.2,<0.3) ; extra == "evaluation" or extra == "all"
Requires-Dist: fastapi (>=0.85,<0.86) ; extra == "serving" or extra == "all"
Requires-Dist: fasttext (>=0.9,<0.10) ; extra == "vectorization" or extra == "all"
Requires-Dist: flask (>=2.2,<3.0) ; extra == "serving" or extra == "all"
Requires-Dist: ftfy (>=6.1,<7.0) ; extra == "preprocessing" or extra == "all"
Requires-Dist: gTTS (>=2.2,<3.0) ; extra == "speech" or extra == "all"
Requires-Dist: gensim (>=4.2,<5.0) ; extra == "core" or extra == "all"
Requires-Dist: gradio (>=3.4,<4.0) ; extra == "serving" or extra == "all"
Requires-Dist: matplotlib (>=3.5,<4.0) ; extra == "visualization" or extra == "all"
Requires-Dist: nltk (>=3.8,<4.0) ; extra == "core" or extra == "all"
Requires-Dist: numpy (>=1.21.0,<2.0.0)
Requires-Dist: onnxruntime (>=1.12,<2.0) ; extra == "serving" or extra == "all"
Requires-Dist: pandas (>=1.3.0,<2.0.0)
Requires-Dist: pyLDAvis (>=3.3,<4.0) ; extra == "topic-modeling" or extra == "all"
Requires-Dist: pyttsx3 (>=2.90,<3.0) ; extra == "speech" or extra == "all"
Requires-Dist: regex (>=2022.7,<2023.0) ; extra == "preprocessing" or extra == "all"
Requires-Dist: scikit-learn (>=1.1,<2.0) ; extra == "vectorization" or extra == "all"
Requires-Dist: seaborn (>=0.11,<0.12) ; extra == "visualization" or extra == "all"
Requires-Dist: sentence-transformers (>=2.2,<3.0) ; extra == "deep-learning" or extra == "all"
Requires-Dist: seqeval (>=1.2,<2.0) ; extra == "evaluation" or extra == "all"
Requires-Dist: spacy (>=3.4,<4.0) ; extra == "core" or extra == "all"
Requires-Dist: stanza (>=1.4,<2.0) ; extra == "core" or extra == "all"
Requires-Dist: streamlit (>=1.12,<2.0) ; extra == "serving" or extra == "all"
Requires-Dist: tensorflow-text (>=2.10,<3.0) ; extra == "deep-learning" or extra == "all"
Requires-Dist: textblob (>=0.17,<0.18) ; extra == "core" or extra == "all"
Requires-Dist: torchtext (>=0.13,<0.14) ; extra == "deep-learning" or extra == "all"
Requires-Dist: tqdm (>=4.62.0,<5.0.0)
Requires-Dist: transformers (>=4.21,<5.0) ; extra == "deep-learning" or extra == "all"
Requires-Dist: translate (>=3.6,<4.0) ; extra == "translation" or extra == "all"
Requires-Dist: vaderSentiment (>=3.3,<4.0) ; extra == "sentiment" or extra == "all"
Requires-Dist: wordcloud (>=1.9,<2.0) ; extra == "visualization" or extra == "all"
